{"name":"Delete a user with an identification deleted previously.","id":"delete-user.;delete-a-user-with-an-identification-deleted-previously.","testSteps":[{"number":1,"description":"Given the admin user are in the remove users section","duration":12,"startTime":"2022-10-17T01:05:38.431018Z[Etc/UTC]","result":"SUCCESS","precondition":false,"level":0},{"number":2,"description":"When the manager user proceed to delete an user that previously was deleted","duration":2811,"startTime":"2022-10-17T01:05:38.444717Z[Etc/UTC]","result":"SUCCESS","precondition":false,"level":0,"children":[{"number":3,"description":"Admin do post","duration":314,"startTime":"2022-10-17T01:05:38.943164Z[Etc/UTC]","result":"SUCCESS","precondition":false,"level":1,"children":[{"number":4,"description":"Admin executes a POST on the resource user/create","duration":302,"startTime":"2022-10-17T01:05:38.949260Z[Etc/UTC]","result":"SUCCESS","precondition":false,"level":2,"children":[{"number":5,"description":"POST https://dummyapi.io/data/v1/user/create","duration":0,"startTime":"2022-10-17T01:05:39.251132Z[Etc/UTC]","result":"SUCCESS","restQuery":{"method":"POST","path":"https://dummyapi.io/data/v1/user/create","content":"{\n    \"title\": \"mr\",\n    \"firstName\": \"Robby\",\n    \"lastName\": \"Miller\",\n    \"gender\": \"male\",\n    \"email\": \"luke.rosenbaum@lulo.com\",\n    \"phone\": \"1-404-601-1073\"\n}","contentType":"application/json","requestHeaders":"app-id\u003d63485f907a44048db04b4361\n\t\t\t\tAccept\u003d*/*\n\t\t\t\tContent-Type\u003dapplication/json; charset\u003dutf-8","requestCookies":"","responseHeaders":"Connection: keep-alive\nContent-Length: 244\nAccess-Control-Allow-Origin: *\nCache-Control: private\nContent-Type: application/json; charset\u003dutf-8\nEtag: W/\"f4-Gjd0qHmIQ9qHEDUq33TZgdVxV58\"\nFunction-Execution-Id: gaix2uqxfhq5\nServer: Google Frontend\nStrict-Transport-Security: max-age\u003d31556926\nX-Cloud-Trace-Context: 4e3b9ca803e96730fdf8d74df86bc283\nX-Country-Code: CO\nAccept-Ranges: bytes\nDate: Mon, 17 Oct 2022 01:05:39 GMT\nX-Served-By: cache-bog2260030-BOG\nX-Cache: MISS\nX-Cache-Hits: 0\nX-Timer: S1665968739.340081,VS0,VE204\nVary: cookie,need-authorization, x-fh-requested-host, accept-encoding\nalt-svc: h3\u003d\":443\";ma\u003d86400,h3-29\u003d\":443\";ma\u003d86400,h3-27\u003d\":443\";ma\u003d86400","responseCookies":"","responseBody":"{\n    \"id\": \"634caa63b523e5013c75109f\",\n    \"title\": \"mr\",\n    \"firstName\": \"Robby\",\n    \"lastName\": \"Miller\",\n    \"gender\": \"male\",\n    \"email\": \"luke.rosenbaum@lulo.com\",\n    \"phone\": \"1-404-601-1073\",\n    \"registerDate\": \"2022-10-17T01:05:39.471Z\",\n    \"updatedDate\": \"2022-10-17T01:05:39.471Z\"\n}","statusCode":200},"precondition":false,"level":3}]},{"number":6,"description":"Admin last response","duration":0,"startTime":"2022-10-17T01:05:39.256424Z[Etc/UTC]","result":"SUCCESS","precondition":false,"level":2}]},{"number":7,"description":"Admin do delete","duration":1505,"startTime":"2022-10-17T01:05:39.265557Z[Etc/UTC]","result":"SUCCESS","precondition":false,"level":1,"children":[{"number":8,"description":"Admin executes a DELETE on the resource user/634caa63b523e5013c75109f","duration":1488,"startTime":"2022-10-17T01:05:39.274456Z[Etc/UTC]","result":"SUCCESS","precondition":false,"level":2,"children":[{"number":9,"description":"DELETE https://dummyapi.io/data/v1/user/634caa63b523e5013c75109f","duration":0,"startTime":"2022-10-17T01:05:40.762636Z[Etc/UTC]","result":"SUCCESS","restQuery":{"method":"DELETE","path":"https://dummyapi.io/data/v1/user/634caa63b523e5013c75109f","content":"","contentType":"application/json","requestHeaders":"app-id\u003d63485f907a44048db04b4361\n\t\t\t\tAccept\u003d*/*\n\t\t\t\tContent-Type\u003dapplication/json; charset\u003dutf-8","requestCookies":"","responseHeaders":"Connection: keep-alive\nContent-Length: 33\nAccess-Control-Allow-Origin: *\nCache-Control: private\nContent-Type: application/json; charset\u003dutf-8\nEtag: W/\"21-ipdugg/+4aFR+/fP063s7klRiTU\"\nFunction-Execution-Id: gaixyu8blmyo\nServer: Google Frontend\nStrict-Transport-Security: max-age\u003d31556926\nX-Cloud-Trace-Context: 69a3b587f357819822cc390ad621be76;o\u003d1\nX-Country-Code: CO\nAccept-Ranges: bytes\nDate: Mon, 17 Oct 2022 01:05:41 GMT\nX-Served-By: cache-bog2260029-BOG\nX-Cache: MISS\nX-Cache-Hits: 0\nX-Timer: S1665968741.780271,VS0,VE271\nVary: cookie,need-authorization, x-fh-requested-host, accept-encoding\nalt-svc: h3\u003d\":443\";ma\u003d86400,h3-29\u003d\":443\";ma\u003d86400,h3-27\u003d\":443\";ma\u003d86400","responseCookies":"","responseBody":"{\n    \"id\": \"634caa63b523e5013c75109f\"\n}","statusCode":200},"precondition":false,"level":3}]},{"number":10,"description":"Admin last response","duration":0,"startTime":"2022-10-17T01:05:40.770110Z[Etc/UTC]","result":"SUCCESS","precondition":false,"level":2}]},{"number":11,"description":"Admin do delete","duration":476,"startTime":"2022-10-17T01:05:40.777014Z[Etc/UTC]","result":"SUCCESS","precondition":false,"level":1,"children":[{"number":12,"description":"Admin executes a DELETE on the resource user/634caa63b523e5013c75109f","duration":458,"startTime":"2022-10-17T01:05:40.788687Z[Etc/UTC]","result":"SUCCESS","precondition":false,"level":2,"children":[{"number":13,"description":"DELETE https://dummyapi.io/data/v1/user/634caa63b523e5013c75109f","duration":0,"startTime":"2022-10-17T01:05:41.246763Z[Etc/UTC]","result":"SUCCESS","restQuery":{"method":"DELETE","path":"https://dummyapi.io/data/v1/user/634caa63b523e5013c75109f","content":"","contentType":"application/json","requestHeaders":"app-id\u003d63485f907a44048db04b4361\n\t\t\t\tAccept\u003d*/*\n\t\t\t\tContent-Type\u003dapplication/json; charset\u003dutf-8","requestCookies":"","responseHeaders":"Connection: keep-alive\nContent-Length: 30\nAccess-Control-Allow-Origin: *\nContent-Type: application/json; charset\u003dutf-8\nEtag: W/\"1e-hQ3POqBPvsvSwNKcIR2tnEBMEfg\"\nFunction-Execution-Id: gaixwrb5ja76\nServer: Google Frontend\nX-Cloud-Trace-Context: 1634de7e3d0cc49f448c6fbb5f014347\nAccept-Ranges: bytes\nDate: Mon, 17 Oct 2022 01:05:41 GMT\nX-Served-By: cache-bog2260033-BOG\nX-Cache: MISS\nX-Cache-Hits: 0\nX-Timer: S1665968741.194673,VS0,VE345\nVary: x-fh-requested-host, accept-encoding\nalt-svc: h3\u003d\":443\";ma\u003d86400,h3-29\u003d\":443\";ma\u003d86400,h3-27\u003d\":443\";ma\u003d86400","responseCookies":"","responseBody":"{\n    \"error\": \"RESOURCE_NOT_FOUND\"\n}","statusCode":404},"precondition":false,"level":3}]},{"number":14,"description":"Admin last response","duration":0,"startTime":"2022-10-17T01:05:41.252463Z[Etc/UTC]","result":"SUCCESS","precondition":false,"level":2}]}]},{"number":15,"description":"Then he should see an error type reference to \"RESOURCE_NOT_FOUND\"","duration":65,"startTime":"2022-10-17T01:05:41.257590Z[Etc/UTC]","result":"SUCCESS","precondition":false,"level":0,"children":[{"number":16,"description":"Then the status code  should be (404)","duration":1,"startTime":"2022-10-17T01:05:41.270070Z[Etc/UTC]","result":"SUCCESS","precondition":false,"level":1},{"number":17,"description":"Then the problems with the schema  should be (false)","duration":2,"startTime":"2022-10-17T01:05:41.286031Z[Etc/UTC]","result":"SUCCESS","precondition":false,"level":1},{"number":18,"description":"Then the error type name  should be \u0027RESOURCE_NOT_FOUND\u0027","duration":13,"startTime":"2022-10-17T01:05:41.306649Z[Etc/UTC]","result":"SUCCESS","precondition":false,"level":1}]}],"userStory":{"id":"delete-user.","storyName":"Delete user.","displayName":"Delete user.","path":"user/delete-user.feature","narrative":"  As a manager user\n  I need a way to delete any kind of user\n  for perform the admin role functions.","type":"feature"},"featureTag":{"name":"User/Delete user.","type":"feature","displayName":"User/Delete user."},"title":"Delete a user with an identification deleted previously.","description":"","backgroundTitle":"","backgroundDescription":"","tags":[{"name":"User/Delete user.","type":"feature","displayName":"Delete user."},{"name":"User","type":"capability","displayName":"User"}],"startTime":"2022-10-17T01:05:38.420740Z[Etc/UTC]","duration":2903,"projectKey":"","isManualTestingUpToDate":false,"manual":false,"testSource":"Cucumber","actors":[{"name":"Admin","can":["browse the web","call an API at https://dummyapi.io/data/v1/"]}],"result":"SUCCESS"}